configuration/__init__.py
configuration/example-config.json
drivers/README.md
drivers/chromedriver
drivers/msedgedriver
features/__init__.py
features/config.py
features/environment.py
features/settings.py
features/test_settings.json
features/example/api_request.feature
features/example/database_connection.feature
features/example/login.feature
features/steps/__init__.py
features/steps/all_steps.py
features/steps/example/api_steps.py
features/steps/example/database_steps.py
features/steps/example/login_steps.py
features/support/actions/example/apiaction.py
features/support/actions/example/databaseaction.py
features/support/actions/example/loginaction.py
features/support/apiclientactions/apiclient.py
features/support/builder/example/examplerequestbuilder.py
features/support/builder/templates/example.xml
features/support/core/__init__.py
features/support/core/elementaction.py
features/support/locators/__init__.py
features/support/locators/general.py
features/support/locators/locator.py
features/support/locators/locatortype.py
features/support/locators/example/loginlocator.py
features/support/pageactions/__init__.py
features/support/pageactions/actionenum.py
features/support/pageactions/basepage.py
features/support/pageactions/commonactions.py
features/support/pageactions/example/loginpage.py
utils/__init__.py
utils/assertutils.py
utils/baseconfigreader.py
utils/configfilereader.py
utils/keyvaultreader.py
utils/testdatahelper.py
utils/utils.py
pytest_behave-1.0.2.dist-info/METADATA
pytest_behave-1.0.2.dist-info/WHEEL
pytest_behave-1.0.2.dist-info/licenses/LICENSE
pytest_behave-1.0.2.dist-info/RECORD
