Metadata-Version: 2.1
Name: pytest-behave
Version: 1.0.2
Summary: A powerful test automation framework designed to provide a comprehensive solution for testing user interfaces and APIs
Project-URL: Homepage, https://github.com/argodevops/pytest-behave
Project-URL: Issues, https://github.com/argodevops/pytest-behave/issues
Author-email: Argo DevOps <info@argodevops.co.uk>
License-File: LICENSE
Classifier: License :: OSI Approved :: Apache Software License
Classifier: Operating System :: OS Independent
Classifier: Programming Language :: Python :: 3.9
Classifier: Programming Language :: Python :: 3.10
Classifier: Programming Language :: Python :: 3.11
Requires-Python: >=3.8
